lucterios/__init__.py
lucterios/standard/Lucterios.ico
lucterios/standard/Lucterios.png
lucterios/standard/__init__.py
lucterios/standard/appli_settings.py
lucterios/standard/build
lucterios/standard/fond.jpg
lucterios/standard/lucterios.css
lucterios/standard/tests.py
lucterios/standard/docs/build_en/doctrees/environment.pickle
lucterios/standard/docs/build_en/doctrees/index.doctree
lucterios/standard/docs/build_fr/doctrees/environment.pickle
lucterios/standard/docs/build_fr/doctrees/index.doctree
lucterios/standard/docs/en/Makefile
lucterios/standard/docs/en/conf.py
lucterios/standard/docs/en/index.rst
lucterios/standard/docs/fr/Makefile
lucterios/standard/docs/fr/conf.py
lucterios/standard/docs/fr/index.rst
lucterios/standard/locale/en/LC_MESSAGES/django.mo
lucterios/standard/locale/en/LC_MESSAGES/django.po
lucterios/standard/locale/fr/LC_MESSAGES/django.mo
lucterios/standard/locale/fr/LC_MESSAGES/django.po
lucterios/standard/pdf/build_fr/doctrees/environment.pickle
lucterios/standard/pdf/build_fr/doctrees/index.doctree
lucterios/standard/pdf/build_fr/doctrees/CORE/architecture.doctree
lucterios/standard/pdf/build_fr/doctrees/CORE/groups.doctree
lucterios/standard/pdf/build_fr/doctrees/CORE/index.doctree
lucterios/standard/pdf/build_fr/doctrees/CORE/password.doctree
lucterios/standard/pdf/build_fr/doctrees/CORE/users.doctree
lucterios/standard/pdf/build_fr/doctrees/contacts/configuration.doctree
lucterios/standard/pdf/build_fr/doctrees/contacts/index.doctree
lucterios/standard/pdf/build_fr/doctrees/contacts/individual.doctree
lucterios/standard/pdf/build_fr/doctrees/contacts/legal_entity.doctree
lucterios/standard/pdf/build_fr/doctrees/contacts/possession.doctree
lucterios/standard/pdf/build_fr/doctrees/documents/configuration.doctree
lucterios/standard/pdf/build_fr/doctrees/documents/editor.doctree
lucterios/standard/pdf/build_fr/doctrees/documents/index.doctree
lucterios/standard/pdf/build_fr/doctrees/documents/shared_document.doctree
lucterios_standard-2.7.0.24101617.dist-info/LICENSE
lucterios_standard-2.7.0.24101617.dist-info/METADATA
lucterios_standard-2.7.0.24101617.dist-info/WHEEL
lucterios_standard-2.7.0.24101617.dist-info/top_level.txt
lucterios_standard-2.7.0.24101617.dist-info/RECORD
